{"biz":{"avax":"https://boards.4chan.org/biz/thread/56810921","bat":"https://boards.4chan.org/biz/thread/56813667","bbbyq":"https://boards.4chan.org/biz/thread/56807646","biz":"https://boards.4chan.org/biz/thread/56823255","cmmg":"https://boards.4chan.org/biz/thread/56800018","dig":"https://boards.4chan.org/biz/thread/56797383","gme":"https://boards.4chan.org/biz/thread/56818731","pmg":"https://boards.4chan.org/biz/thread/56820499","smg":"https://boards.4chan.org/biz/thread/56821894","xmr":"https://boards.4chan.org/biz/thread/56819058","xsg":"https://boards.4chan.org/biz/thread/56807016"},"fit":{"cbt":"https://boards.4chan.org/fit/thread/72928466","fat":"https://boards.4chan.org/fit/thread/72925760","fraud":"https://boards.4chan.org/fit/thread/72929182","mire":"https://boards.4chan.org/fit/thread/72942437","plg":"https://boards.4chan.org/fit/thread/72935405","run":"https://boards.4chan.org/fit/thread/72914712"},"g":{"aicg":"https://boards.4chan.org/g/thread/97628144","aocg":"https://boards.4chan.org/g/thread/97610409","bst":"https://boards.4chan.org/g/thread/97602771","bug":"https://boards.4chan.org/g/thread/97617751","csg":"https://boards.4chan.org/g/thread/97607328","cyb":"https://boards.4chan.org/g/thread/97573829","de3":"https://boards.4chan.org/g/thread/97624516","dmp":"https://boards.4chan.org/g/thread/97576823","fglt":"https://boards.4chan.org/g/thread/97608206","fwt":"https://boards.4chan.org/g/thread/97597096","g":"https://boards.4chan.org/g/thread/97621840","gedg":"https://boards.4chan.org/g/thread/97595555","hare":"https://boards.4chan.org/g/thread/97629522","hpg":"https://boards.4chan.org/g/thread/97596226","iemg":"https://boards.4chan.org/g/thread/97631751","lg":"https://boards.4chan.org/g/thread/97584291","lmg":"https://boards.4chan.org/g/thread/97627335","pcbg":"https://boards.4chan.org/g/thread/97624127","ptg":"https://boards.4chan.org/g/thread/97615316","sdg":"https://boards.4chan.org/g/thread/97626102","sqt":"https://boards.4chan.org/g/thread/97621911","tpg":"https://boards.4chan.org/g/thread/97555062","twg":"https://boards.4chan.org/g/thread/97615002","wdg":"https://boards.4chan.org/g/thread/97620713"}}