{"biz":{"bat":"https://boards.4chan.org/biz/thread/61987419","bbbyq":"https://boards.4chan.org/biz/thread/61997652","biz":"https://boards.4chan.org/biz/thread/61981742","bjhtmu":"https://boards.4chan.org/biz/thread/61994835","gme":"https://boards.4chan.org/biz/thread/61996480","irg":"https://boards.4chan.org/biz/thread/61995178","ksg":"https://boards.4chan.org/biz/thread/61989990","mg":"https://boards.4chan.org/biz/thread/61997211","pmg":"https://boards.4chan.org/biz/thread/61995401","smg":"https://boards.4chan.org/biz/thread/61998104","xmr":"https://boards.4chan.org/biz/thread/61881576","xsg":"https://boards.4chan.org/biz/thread/61987767"},"fit":{"cbt":"https://boards.4chan.org/fit/thread/77146229","fat":"https://boards.4chan.org/fit/thread/77152348","fit":"https://boards.4chan.org/fit/thread/77123852","fph":"https://boards.4chan.org/fit/thread/77154148","fraud":"https://boards.4chan.org/fit/thread/77155149","nutrition":"https://boards.4chan.org/fit/thread/77144689","plg":"https://boards.4chan.org/fit/thread/77109474","qtddtot":"https://boards.4chan.org/fit/thread/77141429","run":"https://boards.4chan.org/fit/thread/77130712","sig":"https://boards.4chan.org/fit/thread/77150558"},"g":{"adt":"https://boards.4chan.org/g/thread/108378992","aicg":"https://boards.4chan.org/g/thread/108390247","ccga":"https://boards.4chan.org/g/thread/108400910","cyb":"https://boards.4chan.org/g/thread/108402028","de3":"https://boards.4chan.org/g/thread/108398965","dmp":"https://boards.4chan.org/g/thread/108401081","dpt":"https://boards.4chan.org/g/thread/108395499","fasm":"https://boards.4chan.org/g/thread/108381052","fglt":"https://boards.4chan.org/g/thread/108399858","fwt":"https://boards.4chan.org/g/thread/108390800","hsg":"https://boards.4chan.org/g/thread/108354801","iemg":"https://boards.4chan.org/g/thread/108371903","ldg":"https://boards.4chan.org/g/thread/108393213","lmg":"https://boards.4chan.org/g/thread/108400151","mkg":"https://boards.4chan.org/g/thread/108401529","pcbg":"https://boards.4chan.org/g/thread/108399613","ptg":"https://boards.4chan.org/g/thread/108401961","sdg":"https://boards.4chan.org/g/thread/108377950","spg":"https://boards.4chan.org/g/thread/108401013","sqt":"https://boards.4chan.org/g/thread/108387207","tpg":"https://boards.4chan.org/g/thread/108391159","twg":"https://boards.4chan.org/g/thread/108387916","utwg":"https://boards.4chan.org/g/thread/108395832","vcg":"https://boards.4chan.org/g/thread/108392928"}}