{"biz":{"bbbyq":"https://boards.4chan.org/biz/thread/57510205","biz":"https://boards.4chan.org/biz/thread/57528825","cmmg":"https://boards.4chan.org/biz/thread/57495112","gme":"https://boards.4chan.org/biz/thread/57522561","icpg":"https://boards.4chan.org/biz/thread/57526198","pmg":"https://boards.4chan.org/biz/thread/57514206","smg":"https://boards.4chan.org/biz/thread/57520815","xmr":"https://boards.4chan.org/biz/thread/57523381","xsg":"https://boards.4chan.org/biz/thread/57519145"},"fit":{"cbt":"https://boards.4chan.org/fit/thread/73519279","fat":"https://boards.4chan.org/fit/thread/73520294","fph":"https://boards.4chan.org/fit/thread/73519301","fraud":"https://boards.4chan.org/fit/thread/73527632","plg":"https://boards.4chan.org/fit/thread/73520066","roon":"https://boards.4chan.org/fit/thread/73512225"},"g":{"aicg":"https://boards.4chan.org/g/thread/98867697","aosg":"https://boards.4chan.org/g/thread/98844062","bst":"https://boards.4chan.org/g/thread/98791510","csg":"https://boards.4chan.org/g/thread/98855083","cyb":"https://boards.4chan.org/g/thread/98807835","de3":"https://boards.4chan.org/g/thread/98852269","dmp":"https://boards.4chan.org/g/thread/98811528","dpt":"https://boards.4chan.org/g/thread/98863452","fglt":"https://boards.4chan.org/g/thread/98858237","fwt":"https://boards.4chan.org/g/thread/98835777","g":"https://boards.4chan.org/g/thread/98869568","hpg":"https://boards.4chan.org/g/thread/98816334","hsg":"https://boards.4chan.org/g/thread/98832264","iemg":"https://boards.4chan.org/g/thread/98848633","mkg":"https://boards.4chan.org/g/thread/98824805","pcbg":"https://boards.4chan.org/g/thread/98858334","ptg":"https://boards.4chan.org/g/thread/98848922","sdg":"https://boards.4chan.org/g/thread/98862337","spg":"https://boards.4chan.org/g/thread/98841991","sqt":"https://boards.4chan.org/g/thread/98868456","textbook":"https://boards.4chan.org/g/thread/98851089","tpg":"https://boards.4chan.org/g/thread/98839798","twg":"https://boards.4chan.org/g/thread/98867984","wdg":"https://boards.4chan.org/g/thread/98832663"}}