{"biz":{"bbbyq":"https://boards.4chan.org/biz/thread/56353559","biz":"https://boards.4chan.org/biz/thread/56367955","cmmg":"https://boards.4chan.org/biz/thread/56313451","gme":"https://boards.4chan.org/biz/thread/56361621","nvda":"https://boards.4chan.org/biz/thread/56365381","pmg":"https://boards.4chan.org/biz/thread/56365232","smg":"https://boards.4chan.org/biz/thread/56364481","tfg":"https://boards.4chan.org/biz/thread/56366775","xmr":"https://boards.4chan.org/biz/thread/56309959","xsg":"https://boards.4chan.org/biz/thread/56351095"},"fit":{"cbt":"https://boards.4chan.org/fit/thread/72528778","fit":"https://boards.4chan.org/fit/thread/72527611","fph":"https://boards.4chan.org/fit/thread/72526685","fraud":"https://boards.4chan.org/fit/thread/72527769","mire":"https://boards.4chan.org/fit/thread/72527285","plg":"https://boards.4chan.org/fit/thread/72512560","rth":"https://boards.4chan.org/fit/thread/72529892","run":"https://boards.4chan.org/fit/thread/72504198"},"g":{"aiag":"https://boards.4chan.org/g/thread/96685620","aicg":"https://boards.4chan.org/g/thread/96685401","aig":"https://boards.4chan.org/g/thread/96671585","chad":"https://boards.4chan.org/g/thread/96638634","csg":"https://boards.4chan.org/g/thread/96650829","de3":"https://boards.4chan.org/g/thread/96687196","dmp":"https://boards.4chan.org/g/thread/96618766","dpt":"https://boards.4chan.org/g/thread/96688649","fglt":"https://boards.4chan.org/g/thread/96667287","fwt":"https://boards.4chan.org/g/thread/96684013","g":"https://boards.4chan.org/g/thread/96685495","hifi":"https://boards.4chan.org/g/thread/96686152","hsg":"https://boards.4chan.org/g/thread/96687488","iemg":"https://boards.4chan.org/g/thread/96664340","lmg":"https://boards.4chan.org/g/thread/96675096","mg":"https://boards.4chan.org/g/thread/96686647","mkg":"https://boards.4chan.org/g/thread/96677345","nexus":"https://boards.4chan.org/g/thread/96682639","pcbg":"https://boards.4chan.org/g/thread/96686901","psg":"https://boards.4chan.org/g/thread/96559980","ptg":"https://boards.4chan.org/g/thread/96675100","sdg":"https://boards.4chan.org/g/thread/96682887","spg":"https://boards.4chan.org/g/thread/96666093","sqt":"https://boards.4chan.org/g/thread/96635717","tpg":"https://boards.4chan.org/g/thread/96649353","twg":"https://boards.4chan.org/g/thread/96681995","wdg":"https://boards.4chan.org/g/thread/96654942"}}