{"biz":{"avax":"https://boards.4chan.org/biz/thread/56609918","bbby":"https://boards.4chan.org/biz/thread/56632409","biz":"https://boards.4chan.org/biz/thread/56630064","cmmg":"https://boards.4chan.org/biz/thread/56609598","gme":"https://boards.4chan.org/biz/thread/56625320","pmg":"https://boards.4chan.org/biz/thread/56620320","smg":"https://boards.4chan.org/biz/thread/56630582","xmr":"https://boards.4chan.org/biz/thread/56613128","xsg":"https://boards.4chan.org/biz/thread/56632534"},"fit":{"fat":"https://boards.4chan.org/fit/thread/72776629","fit":"https://boards.4chan.org/fit/thread/72779353","fitbar":"https://boards.4chan.org/fit/thread/72771216","fph":"https://boards.4chan.org/fit/thread/72780246","mire":"https://boards.4chan.org/fit/thread/72769561","plg":"https://boards.4chan.org/fit/thread/72770776","run":"https://boards.4chan.org/fit/thread/72752146"},"g":{"aicg":"https://boards.4chan.org/g/thread/97241317","bst":"https://boards.4chan.org/g/thread/97168419","chad":"https://boards.4chan.org/g/thread/97195992","csg":"https://boards.4chan.org/g/thread/97235756","de3":"https://boards.4chan.org/g/thread/97237363","dmp":"https://boards.4chan.org/g/thread/97210902","dpt":"https://boards.4chan.org/g/thread/97209481","fglt":"https://boards.4chan.org/g/thread/97228113","flet":"https://boards.4chan.org/g/thread/97125679","fwt":"https://boards.4chan.org/g/thread/97218554","g":"https://boards.4chan.org/g/thread/97239013","gedg":"https://boards.4chan.org/g/thread/97192095","hifi":"https://boards.4chan.org/g/thread/97233227","hpg":"https://boards.4chan.org/g/thread/97190966","hsg":"https://boards.4chan.org/g/thread/97194480","iemg":"https://boards.4chan.org/g/thread/97235757","lmg":"https://boards.4chan.org/g/thread/97239783","lwt":"https://boards.4chan.org/g/thread/97234112","mkg":"https://boards.4chan.org/g/thread/97127864","pcbg":"https://boards.4chan.org/g/thread/97234618","psg":"https://boards.4chan.org/g/thread/97215815","ptg":"https://boards.4chan.org/g/thread/97239301","sdg":"https://boards.4chan.org/g/thread/97237208","sovl":"https://boards.4chan.org/g/thread/97245540","spg":"https://boards.4chan.org/g/thread/97230077","sqt":"https://boards.4chan.org/g/thread/97208376","tpg":"https://boards.4chan.org/g/thread/97206943","twg":"https://boards.4chan.org/g/thread/97231527","wdg":"https://boards.4chan.org/g/thread/97219511"}}