{"biz":{"bbbyq":"https://boards.4chan.org/biz/thread/57494993","biz":"https://boards.4chan.org/biz/thread/57484483","cmmg":"https://boards.4chan.org/biz/thread/57495112","cng":"https://boards.4chan.org/biz/thread/57498147","crypto":"https://boards.4chan.org/biz/thread/57497490","dig":"https://boards.4chan.org/biz/thread/57474325","gme":"https://boards.4chan.org/biz/thread/57494221","mac":"https://boards.4chan.org/biz/thread/57497225","pmg":"https://boards.4chan.org/biz/thread/57484654","smg":"https://boards.4chan.org/biz/thread/57493508","wpg":"https://boards.4chan.org/biz/thread/57498899","xmr":"https://boards.4chan.org/biz/thread/57485222","xsg":"https://boards.4chan.org/biz/thread/57478470"},"fit":{"cbt":"https://boards.4chan.org/fit/thread/73491942","fat":"https://boards.4chan.org/fit/thread/73494634","feelsbar":"https://boards.4chan.org/fit/thread/73494746","fit":"https://boards.4chan.org/fit/thread/73503781","fph":"https://boards.4chan.org/fit/thread/73499556","fraud":"https://boards.4chan.org/fit/thread/73492526","mire":"https://boards.4chan.org/fit/thread/73492385","plg":"https://boards.4chan.org/fit/thread/73495779","plrg":"https://boards.4chan.org/fit/thread/73502382","roon":"https://boards.4chan.org/fit/thread/73484965"},"g":{"aicg":"https://boards.4chan.org/g/thread/98814693","bst":"https://boards.4chan.org/g/thread/98791510","cyb":"https://boards.4chan.org/g/thread/98807835","de3":"https://boards.4chan.org/g/thread/98808814","dmp":"https://boards.4chan.org/g/thread/98811528","dpt":"https://boards.4chan.org/g/thread/98806206","fglt":"https://boards.4chan.org/g/thread/98805190","fwt":"https://boards.4chan.org/g/thread/98777636","gedg":"https://boards.4chan.org/g/thread/98796412","hpg":"https://boards.4chan.org/g/thread/98816334","hsg":"https://boards.4chan.org/g/thread/98798393","iemg":"https://boards.4chan.org/g/thread/98804569","lmg":"https://boards.4chan.org/g/thread/98815323","mkg":"https://boards.4chan.org/g/thread/98700535","nvim":"https://boards.4chan.org/g/thread/98814772","pcbg":"https://boards.4chan.org/g/thread/98810590","ptg":"https://boards.4chan.org/g/thread/98804876","sdg":"https://boards.4chan.org/g/thread/98810566","spg":"https://boards.4chan.org/g/thread/98804933","sqt":"https://boards.4chan.org/g/thread/98804599","tpg":"https://boards.4chan.org/g/thread/98754884","twg":"https://boards.4chan.org/g/thread/98800457","wdg":"https://boards.4chan.org/g/thread/98793983"}}